README.rst
setup.py
econf/__init__.py
econf.egg-info/PKG-INFO
econf.egg-info/SOURCES.txt
econf.egg-info/dependency_links.txt
econf.egg-info/top_level.txt