Metadata-Version: 1.1
Name: econf
Version: 0.1.4
Summary: easy to define and reference config options
Home-page: http://github.com/wangst321/econf.git
Author: WangST
Author-email: shaotian.wang@ele.me
License: UNKNOWN
Platform: UNKNOWN
Classifier: Development Status :: 2 - Pre-Alpha
Classifier: Intended Audience :: Developers
Classifier: Natural Language :: English
Classifier: Programming Language :: Python :: 2
Classifier: Programming Language :: Python :: 2.7
Classifier: Programming Language :: Python :: 3
Classifier: Programming Language :: Python :: 3.4
